{
  "manifestVersion": "3.2",
  "proxies": [
    {
      "address": "0x957dfF79d47fE09Ee9069c2A170BC9E65D13e9a1",
      "txHash": "0x5dc89809f5c7e6b5b820466fbf2ae6179d31297a4bfd9ce90a2711c7e9cda2c3",
      "kind": "uups"
    },
    {
      "address": "0xcA37d11091eAfd87b8b29b50498338393e89595F",
      "txHash": "0xd3074c0e15a4f1239dfff690774c60d511d4fafc7571d8b52f9a615698079544",
      "kind": "uups"
    }
  ],
  "impls": {
    "15c5df5b82287e3899f92778228c23881d1f82f1c99012a41ca23991444fdce7": {
      "address": "0x1BEb89123613Db92028e3E5cE2F2625A497575Dd",
      "txHash": "0xd00b8c3a6bf266c23d6c1f93affc0e17fe0551a71db45d83291e7a9f49caa912",
      "layout": {
        "solcVersion": "0.8.28",
        "storage": [
          {
            "label": "dummyNum",
            "offset": 0,
            "slot": "0",
            "type": "t_uint256",
            "contract": "UUPSDummyContract",
            "src": "contracts/UUPSContract.sol:9"
          },
          {
            "label": "list",
            "offset": 0,
            "slot": "1",
            "type": "t_mapping(t_uint256,t_address)",
            "contract": "UUPSDummyContract",
            "src": "contracts/UUPSContract.sol:10"
          }
        ],
        "types": {
          "t_address": {
            "label": "address",
            "numberOfBytes": "20"
          },
          "t_bool": {
            "label": "bool",
            "numberOfBytes": "1"
          },
          "t_struct(InitializableStorage)65_storage": {
            "label": "struct Initializable.InitializableStorage",
            "members": [
              {
                "label": "_initialized",
                "type": "t_uint64",
                "offset": 0,
                "slot": "0"
              },
              {
                "label": "_initializing",
                "type": "t_bool",
                "offset": 8,
                "slot": "0"
              }
            ],
            "numberOfBytes": "32"
          },
          "t_struct(OwnableStorage)14_storage": {
            "label": "struct OwnableUpgradeable.OwnableStorage",
            "members": [
              {
                "label": "_owner",
                "type": "t_address",
                "offset": 0,
                "slot": "0"
              }
            ],
            "numberOfBytes": "32"
          },
          "t_uint64": {
            "label": "uint64",
            "numberOfBytes": "8"
          },
          "t_mapping(t_uint256,t_address)": {
            "label": "mapping(uint256 => address)",
            "numberOfBytes": "32"
          },
          "t_uint256": {
            "label": "uint256",
            "numberOfBytes": "32"
          }
        },
        "namespaces": {
          "erc7201:openzeppelin.storage.Ownable": [
            {
              "contract": "OwnableUpgradeable",
              "label": "_owner",
              "type": "t_address",
              "src": "@openzeppelin/contracts-upgradeable/access/OwnableUpgradeable.sol:24",
              "offset": 0,
              "slot": "0"
            }
          ],
          "erc7201:openzeppelin.storage.Initializable": [
            {
              "contract": "Initializable",
              "label": "_initialized",
              "type": "t_uint64",
              "src": "@openzeppelin/contracts-upgradeable/proxy/utils/Initializable.sol:69",
              "offset": 0,
              "slot": "0"
            },
            {
              "contract": "Initializable",
              "label": "_initializing",
              "type": "t_bool",
              "src": "@openzeppelin/contracts-upgradeable/proxy/utils/Initializable.sol:73",
              "offset": 8,
              "slot": "0"
            }
          ]
        }
      }
    },
    "13c02ce0a5b7353060df102847053663323e8f968d9bd3b25600365ee2d22cbb": {
      "address": "0xb835494f57AC6C58d1c9DD2415F8Bd99FfAC8c70",
      "txHash": "0x89fc497fa9ee0dad28bc09bb4133472bde58c907c3d31276ec2a469bd16b64fa",
      "layout": {
        "solcVersion": "0.8.20",
        "storage": [
          {
            "label": "dummyNum",
            "offset": 0,
            "slot": "0",
            "type": "t_uint256",
            "contract": "UUPSDummyContract",
            "src": "contracts/UUPSDummyContract.sol:9"
          },
          {
            "label": "list",
            "offset": 0,
            "slot": "1",
            "type": "t_mapping(t_uint256,t_address)",
            "contract": "UUPSDummyContract",
            "src": "contracts/UUPSDummyContract.sol:10"
          }
        ],
        "types": {
          "t_address": {
            "label": "address",
            "numberOfBytes": "20"
          },
          "t_bool": {
            "label": "bool",
            "numberOfBytes": "1"
          },
          "t_struct(InitializableStorage)65_storage": {
            "label": "struct Initializable.InitializableStorage",
            "members": [
              {
                "label": "_initialized",
                "type": "t_uint64",
                "offset": 0,
                "slot": "0"
              },
              {
                "label": "_initializing",
                "type": "t_bool",
                "offset": 8,
                "slot": "0"
              }
            ],
            "numberOfBytes": "32"
          },
          "t_struct(OwnableStorage)14_storage": {
            "label": "struct OwnableUpgradeable.OwnableStorage",
            "members": [
              {
                "label": "_owner",
                "type": "t_address",
                "offset": 0,
                "slot": "0"
              }
            ],
            "numberOfBytes": "32"
          },
          "t_uint64": {
            "label": "uint64",
            "numberOfBytes": "8"
          },
          "t_mapping(t_uint256,t_address)": {
            "label": "mapping(uint256 => address)",
            "numberOfBytes": "32"
          },
          "t_uint256": {
            "label": "uint256",
            "numberOfBytes": "32"
          }
        },
        "namespaces": {
          "erc7201:openzeppelin.storage.Ownable": [
            {
              "contract": "OwnableUpgradeable",
              "label": "_owner",
              "type": "t_address",
              "src": "@openzeppelin/contracts-upgradeable/access/OwnableUpgradeable.sol:24",
              "offset": 0,
              "slot": "0"
            }
          ],
          "erc7201:openzeppelin.storage.Initializable": [
            {
              "contract": "Initializable",
              "label": "_initialized",
              "type": "t_uint64",
              "src": "@openzeppelin/contracts-upgradeable/proxy/utils/Initializable.sol:69",
              "offset": 0,
              "slot": "0"
            },
            {
              "contract": "Initializable",
              "label": "_initializing",
              "type": "t_bool",
              "src": "@openzeppelin/contracts-upgradeable/proxy/utils/Initializable.sol:73",
              "offset": 8,
              "slot": "0"
            }
          ]
        }
      }
    }
  }
}
